anki_cli_unofficial-1.0.3.data/scripts/anki-cli-unofficial
ankicli/__init__.py
ankicli/cli.py
ankicli/loader.py
anki_cli_unofficial-1.0.3.dist-info/LICENSE
anki_cli_unofficial-1.0.3.dist-info/METADATA
anki_cli_unofficial-1.0.3.dist-info/WHEEL
anki_cli_unofficial-1.0.3.dist-info/top_level.txt
anki_cli_unofficial-1.0.3.dist-info/RECORD
