Metadata-Version: 2.1
Name: anki-cli-unofficial
Version: 1.0.3
Summary: A CLI to load flashcards in Anki2
Home-page: http://github.com/julien-sobczak/anki-cli
Author: Julien Sobczak
License: UNKNOWN
Platform: UNKNOWN
Classifier: Programming Language :: Python :: 3
Classifier: License :: OSI Approved :: MIT License
Classifier: Operating System :: OS Independent
Requires-Python: >=3.6
License-File: LICENSE
Requires-Dist: setuptools
Requires-Dist: pyyaml
